{
  "bg": 100, 
  "temp": "absolute", 
  "snoozeBG": 82, 
  "timestamp": "2016-06-19T00:52:19.458405", 
  "missing": [
    "duration", 
    "rate"
  ], 
  "reason": "Eventual BG 74<90, Snooze BG 82, temp 0 ~< req 0.12U/hr", 
  "eventualBG": 74, 
  "error": "missing required input fields", 
  "input": {
    "reason": "Eventual BG 74<90, Snooze BG 82, temp 0 ~< req 0.12U/hr", 
    "bg": 100, 
    "eventualBG": 74, 
    "temp": "absolute", 
    "snoozeBG": 82, 
    "mealAssist": "Off: Carbs: undefined Boluses: undefined ISF: 40, Target: 90 Deviation: 4 BGI: -2.4", 
    "tick": -1
  }, 
  "mealAssist": "Off: Carbs: undefined Boluses: undefined ISF: 40, Target: 90 Deviation: 4 BGI: -2.4", 
  "tick": -1
}