[
  {
    "device": "openaps://dmapsE1", 
    "created_at": "2016-07-10T16:12:23.172Z", 
    "pump": {
      "battery": {
        "status": "normal", 
        "voltage": 1.54
      }, 
      "status": {
        "status": "normal", 
        "timestamp": "2016-07-10T16:11:36.000Z", 
        "bolusing": true, 
        "suspended": false
      }, 
      "reservoir": 123.775, 
      "clock": "2016-07-10T10:10:36-06:00"
    }, 
    "_id": "578273e72003490b001bd9e3", 
    "openaps": {
      "suggested": {
        "bg": 74, 
        "temp": "absolute", 
        "snoozeBG": 2, 
        "timestamp": "2016-07-10T16:12:06.000Z", 
        "reason": "Eventual BG 0 < 90, but Delta +5 > Exp. Delta -2.7; setting current basal of 0.4 as temp", 
        "rate": 0.4, 
        "eventualBG": 0, 
        "duration": 30, 
        "mealAssist": "Off: Carbs: undefined Boluses: undefined ISF: 50, Target: 90 Deviation: 28 BGI: -4.53", 
        "tick": "+5"
      }, 
      "iob": {
        "netbasalinsulin": 1.75, 
        "timestamp": "2016-07-10T16:12:04.000Z", 
        "activity": 0.0181, 
        "basaliob": 1.58, 
        "hightempinsulin": 1.9, 
        "bolussnooze": 0.033, 
        "iob": 2.037
      }, 
      "enacted": {
        "bg": 74, 
        "temp": "absolute", 
        "snoozeBG": 2, 
        "timestamp": "2016-07-10T16:12:08.000Z", 
        "reason": "Eventual BG 0 < 90, but Delta +5 > Exp. Delta -2.7; setting current basal of 0.4 as temp", 
        "rate": 0.4, 
        "eventualBG": 0, 
        "duration": 30, 
        "mealAssist": "Off: Carbs: undefined Boluses: undefined ISF: 50, Target: 90 Deviation: 28 BGI: -4.53", 
        "tick": "+5"
      }
    }
  }
]